py_main/__init__.py
py_main/main.py
py_main/utils/__init__.py
py_main/utils/algrithms/__init__.py
py_main/utils/algrithms/fishercal.py
py_main/utils/algrithms/hypergeom.py
py_main/utils/algrithms/mat_multi_hypergeom.py
py_main/utils/data_processing/__init__.py
py_main/utils/data_processing/data_process.py
py_main/utils/data_processing/data_processv2.py
py_main/utils/data_processing/out_put_file.py
py_main/utils/data_processing/to_10x.py
py_main/utils/data_processing/to_10x_batch.py
py_main/utils/gui/__init__.py
py_main/utils/gui/main_win_setup.py
py_main/utils/gui/winform.py
SingleCellFEM-0.1.dist-info/METADATA
SingleCellFEM-0.1.dist-info/WHEEL
SingleCellFEM-0.1.dist-info/top_level.txt
SingleCellFEM-0.1.dist-info/RECORD
